<?xml version="1.0" encoding="UTF-8"?>
<?xml-stylesheet href="/xml/XSLT/panelfile.xsl" type="text/xsl"?>
<!DOCTYPE layout-config SYSTEM "layout-config-2-5-2.dtd">

<layout-config>
  <paneleditor class="jmri.jmrit.display.panelEditor.configurexml.PanelEditorXml" name="Turntable Control" x="20" y="22" height="580" width="420" editable="no" positionable="yes" showcoordinates="no" controlling="yes" hide="yes" panelmenu="yes">

    <positionablelabel y="45" text="West Lead" x="1" forcecontroloff="false" fixed="false" showtooltip="true" class="jmri.jmrit.display.configurexml.PositionableLabelXml" level="5" size="13" style="0" />
    <sensoricon        y="45" sensor="CS2022" x="82" level="10" active="resources/icons/mediumschematics/LEDs/AMBERLED.gif" inactive="resources/icons/mediumschematics/LEDs/whiteLED.gif" unknown="resources/icons/mediumschematics/LEDs/GRAYLED.gif" inconsistent="resources/icons/mediumschematics/LEDs/GRAYLED.gif" rotate="0" forcecontroloff="false" momentary="true" class="jmri.jmrit.display.configurexml.SensorIconXml" />
    <memoryicon        y="45" memory="IMTRKWESTLEADH1" x="110" level="5" text="1899" size="13" style="0" selectable="no" class="jmri.jmrit.display.configurexml.MemoryIconXml" defaulticon="resources/icons/misc/X-red.gif" />
    <memoryicon        y="45" memory="IMTRKWESTLEADH2" x="170" level="5" text="1899" size="13" style="0" selectable="no" class="jmri.jmrit.display.configurexml.MemoryIconXml" defaulticon="resources/icons/misc/X-red.gif" />
    <memoryicon        y="45" memory="IMTRKWESTLEADT1" x="280" level="5" text="8503" size="13" style="0" selectable="no" class="jmri.jmrit.display.configurexml.MemoryIconXml" defaulticon="resources/icons/misc/X-red.gif" />
    <memoryicon        y="45" memory="IMTRKWESTLEADT2" x="340" level="5" text="8503" size="13" style="0" selectable="no" class="jmri.jmrit.display.configurexml.MemoryIconXml" defaulticon="resources/icons/misc/X-red.gif" />

    <positionablelabel y="65" text="Mallet 1" x="7" forcecontroloff="false" fixed="false" showtooltip="true" class="jmri.jmrit.display.configurexml.PositionableLabelXml" level="5" size="13" style="0" />
    <sensoricon        y="65" sensor="CS2021" x="82" level="10" active="resources/icons/mediumschematics/LEDs/AMBERLED.gif" inactive="resources/icons/mediumschematics/LEDs/whiteLED.gif" unknown="resources/icons/mediumschematics/LEDs/GRAYLED.gif" inconsistent="resources/icons/mediumschematics/LEDs/GRAYLED.gif" rotate="0" forcecontroloff="false" momentary="true" class="jmri.jmrit.display.configurexml.SensorIconXml" />
    <memoryicon        y="65" memory="IMTRKMALLET1H1" x="110" level="5" text="1899" size="13" style="0" selectable="no" class="jmri.jmrit.display.configurexml.MemoryIconXml" defaulticon="resources/icons/misc/X-red.gif" />
    <memoryicon        y="65" memory="IMTRKMALLET1H2" x="170" level="5" text="1899" size="13" style="0" selectable="no" class="jmri.jmrit.display.configurexml.MemoryIconXml" defaulticon="resources/icons/misc/X-red.gif" />
    <memoryicon        y="65" memory="IMTRKMALLET1T1" x="280" level="5" text="8503" size="13" style="0" selectable="no" class="jmri.jmrit.display.configurexml.MemoryIconXml" defaulticon="resources/icons/misc/X-red.gif" />
    <memoryicon        y="65" memory="IMTRKMALLET1T2" x="340" level="5" text="8503" size="13" style="0" selectable="no" class="jmri.jmrit.display.configurexml.MemoryIconXml" defaulticon="resources/icons/misc/X-red.gif" />

    <positionablelabel y="85" text="Mallet 2" x="7" forcecontroloff="false" fixed="false" showtooltip="true" class="jmri.jmrit.display.configurexml.PositionableLabelXml" level="5" size="13" style="0" />
    <sensoricon        y="85" sensor="CS2020" x="82" level="10" active="resources/icons/mediumschematics/LEDs/AMBERLED.gif" inactive="resources/icons/mediumschematics/LEDs/whiteLED.gif" unknown="resources/icons/mediumschematics/LEDs/GRAYLED.gif" inconsistent="resources/icons/mediumschematics/LEDs/GRAYLED.gif" rotate="0" forcecontroloff="false" momentary="true" class="jmri.jmrit.display.configurexml.SensorIconXml" />
    <memoryicon        y="85" memory="IMTRKMALLET2H1" x="110" level="5" text="1899" size="13" style="0" selectable="no" class="jmri.jmrit.display.configurexml.MemoryIconXml" defaulticon="resources/icons/misc/X-red.gif" />
    <memoryicon        y="85" memory="IMTRKMALLET2H2" x="170" level="5" text="1899" size="13" style="0" selectable="no" class="jmri.jmrit.display.configurexml.MemoryIconXml" defaulticon="resources/icons/misc/X-red.gif" />
    <memoryicon        y="85" memory="IMTRKMALLET2T1" x="280" level="5" text="8503" size="13" style="0" selectable="no" class="jmri.jmrit.display.configurexml.MemoryIconXml" defaulticon="resources/icons/misc/X-red.gif" />
    <memoryicon        y="85" memory="IMTRKMALLET2T2" x="340" level="5" text="8503" size="13" style="0" selectable="no" class="jmri.jmrit.display.configurexml.MemoryIconXml" defaulticon="resources/icons/misc/X-red.gif" />

    <positionablelabel y="105" text="Sand" x="19" forcecontroloff="false" fixed="false" showtooltip="true" class="jmri.jmrit.display.configurexml.PositionableLabelXml" level="5" size="13" style="0" />
    <sensoricon        y="105" sensor="CS2019" x="82" level="10" active="resources/icons/mediumschematics/LEDs/AMBERLED.gif" inactive="resources/icons/mediumschematics/LEDs/whiteLED.gif" unknown="resources/icons/mediumschematics/LEDs/GRAYLED.gif" inconsistent="resources/icons/mediumschematics/LEDs/GRAYLED.gif" rotate="0" forcecontroloff="false" momentary="true" class="jmri.jmrit.display.configurexml.SensorIconXml" />
    <memoryicon        y="105" memory="IMTRKSANDH1" x="110" level="5" text="1899" size="13" style="0" selectable="no" class="jmri.jmrit.display.configurexml.MemoryIconXml" defaulticon="resources/icons/misc/X-red.gif" />
    <memoryicon        y="105" memory="IMTRKSANDH2" x="170" level="5" text="1899" size="13" style="0" selectable="no" class="jmri.jmrit.display.configurexml.MemoryIconXml" defaulticon="resources/icons/misc/X-red.gif" />
    <memoryicon        y="105" memory="IMTRKSANDT1" x="280" level="5" text="8503" size="13" style="0" selectable="no" class="jmri.jmrit.display.configurexml.MemoryIconXml" defaulticon="resources/icons/misc/X-red.gif" />
    <memoryicon        y="105" memory="IMTRKSANDT2" x="340" level="5" text="8503" size="13" style="0" selectable="no" class="jmri.jmrit.display.configurexml.MemoryIconXml" defaulticon="resources/icons/misc/X-red.gif" />

    <positionablelabel y="125" text="Track 1" x="19" forcecontroloff="false" fixed="false" showtooltip="true" class="jmri.jmrit.display.configurexml.PositionableLabelXml" level="5" size="13" style="0" />
    <sensoricon        y="125" sensor="CS2001" x="82" level="10" active="resources/icons/mediumschematics/LEDs/AMBERLED.gif" inactive="resources/icons/mediumschematics/LEDs/whiteLED.gif" unknown="resources/icons/mediumschematics/LEDs/GRAYLED.gif" inconsistent="resources/icons/mediumschematics/LEDs/GRAYLED.gif" rotate="0" forcecontroloff="false" momentary="true" class="jmri.jmrit.display.configurexml.SensorIconXml" />
    <memoryicon        y="125" memory="IMTRK1H1" x="110" level="5" text="1899" size="13" style="0" selectable="no" class="jmri.jmrit.display.configurexml.MemoryIconXml" defaulticon="resources/icons/misc/X-red.gif" />
    <memoryicon        y="125" memory="IMTRK1H2" x="170" level="5" text="1899" size="13" style="0" selectable="no" class="jmri.jmrit.display.configurexml.MemoryIconXml" defaulticon="resources/icons/misc/X-red.gif" />
    <memoryicon        y="125" memory="IMTRK1T1" x="280" level="5" text="8503" size="13" style="0" selectable="no" class="jmri.jmrit.display.configurexml.MemoryIconXml" defaulticon="resources/icons/misc/X-red.gif" />
    <memoryicon        y="125" memory="IMTRK1T2" x="340" level="5" text="8503" size="13" style="0" selectable="no" class="jmri.jmrit.display.configurexml.MemoryIconXml" defaulticon="resources/icons/misc/X-red.gif" />

    <positionablelabel y="145" text="Track 2" x="19" forcecontroloff="false" fixed="false" showtooltip="true" class="jmri.jmrit.display.configurexml.PositionableLabelXml" level="5" size="13" style="0" />
    <sensoricon        y="145" sensor="CS2002" x="82" level="10" active="resources/icons/mediumschematics/LEDs/AMBERLED.gif" inactive="resources/icons/mediumschematics/LEDs/whiteLED.gif" unknown="resources/icons/mediumschematics/LEDs/GRAYLED.gif" inconsistent="resources/icons/mediumschematics/LEDs/GRAYLED.gif" rotate="0" forcecontroloff="false" momentary="true" class="jmri.jmrit.display.configurexml.SensorIconXml" />
    <memoryicon        y="145" memory="IMTRK2H1" x="110" level="5" text="1899" size="13" style="0" selectable="no" class="jmri.jmrit.display.configurexml.MemoryIconXml" defaulticon="resources/icons/misc/X-red.gif" />
    <memoryicon        y="145" memory="IMTRK2H2" x="170" level="5" text="1899" size="13" style="0" selectable="no" class="jmri.jmrit.display.configurexml.MemoryIconXml" defaulticon="resources/icons/misc/X-red.gif" />
    <memoryicon        y="145" memory="IMTRK2T1" x="280" level="5" text="8503" size="13" style="0" selectable="no" class="jmri.jmrit.display.configurexml.MemoryIconXml" defaulticon="resources/icons/misc/X-red.gif" />
    <memoryicon        y="145" memory="IMTRK2T2" x="340" level="5" text="8503" size="13" style="0" selectable="no" class="jmri.jmrit.display.configurexml.MemoryIconXml" defaulticon="resources/icons/misc/X-red.gif" />

    <positionablelabel y="165" text="Track 3" x="19" forcecontroloff="false" fixed="false" showtooltip="true" class="jmri.jmrit.display.configurexml.PositionableLabelXml" level="5" size="13" style="0" />
    <sensoricon        y="165" sensor="CS2003" x="82" level="10" active="resources/icons/mediumschematics/LEDs/AMBERLED.gif" inactive="resources/icons/mediumschematics/LEDs/whiteLED.gif" unknown="resources/icons/mediumschematics/LEDs/GRAYLED.gif" inconsistent="resources/icons/mediumschematics/LEDs/GRAYLED.gif" rotate="0" forcecontroloff="false" momentary="true" class="jmri.jmrit.display.configurexml.SensorIconXml" />
    <memoryicon        y="165" memory="IMTRK3H1" x="110" level="5" text="1899" size="13" style="0" selectable="no" class="jmri.jmrit.display.configurexml.MemoryIconXml" defaulticon="resources/icons/misc/X-red.gif" />
    <memoryicon        y="165" memory="IMTRK3H2" x="170" level="5" text="1899" size="13" style="0" selectable="no" class="jmri.jmrit.display.configurexml.MemoryIconXml" defaulticon="resources/icons/misc/X-red.gif" />
    <memoryicon        y="165" memory="IMTRK3T1" x="280" level="5" text="8503" size="13" style="0" selectable="no" class="jmri.jmrit.display.configurexml.MemoryIconXml" defaulticon="resources/icons/misc/X-red.gif" />
    <memoryicon        y="165" memory="IMTRK3T2" x="340" level="5" text="8503" size="13" style="0" selectable="no" class="jmri.jmrit.display.configurexml.MemoryIconXml" defaulticon="resources/icons/misc/X-red.gif" />

    <positionablelabel y="185" text="Track 4" x="19" forcecontroloff="false" fixed="false" showtooltip="true" class="jmri.jmrit.display.configurexml.PositionableLabelXml" level="5" size="13" style="0" />
    <sensoricon        y="185" sensor="CS2004" x="82" level="10" active="resources/icons/mediumschematics/LEDs/AMBERLED.gif" inactive="resources/icons/mediumschematics/LEDs/whiteLED.gif" unknown="resources/icons/mediumschematics/LEDs/GRAYLED.gif" inconsistent="resources/icons/mediumschematics/LEDs/GRAYLED.gif" rotate="0" forcecontroloff="false" momentary="true" class="jmri.jmrit.display.configurexml.SensorIconXml" />
    <memoryicon        y="185" memory="IMTRK4H1" x="110" level="5" text="1899" size="13" style="0" selectable="no" class="jmri.jmrit.display.configurexml.MemoryIconXml" defaulticon="resources/icons/misc/X-red.gif" />
    <memoryicon        y="185" memory="IMTRK4H2" x="170" level="5" text="1899" size="13" style="0" selectable="no" class="jmri.jmrit.display.configurexml.MemoryIconXml" defaulticon="resources/icons/misc/X-red.gif" />
    <memoryicon        y="185" memory="IMTRK4T1" x="280" level="5" text="8503" size="13" style="0" selectable="no" class="jmri.jmrit.display.configurexml.MemoryIconXml" defaulticon="resources/icons/misc/X-red.gif" />
    <memoryicon        y="185" memory="IMTRK4T2" x="340" level="5" text="8503" size="13" style="0" selectable="no" class="jmri.jmrit.display.configurexml.MemoryIconXml" defaulticon="resources/icons/misc/X-red.gif" />

    <positionablelabel y="205" text="Track 5" x="19" forcecontroloff="false" fixed="false" showtooltip="true" class="jmri.jmrit.display.configurexml.PositionableLabelXml" level="5" size="13" style="0" />
    <sensoricon        y="205" sensor="CS2005" x="82" level="10" active="resources/icons/mediumschematics/LEDs/AMBERLED.gif" inactive="resources/icons/mediumschematics/LEDs/whiteLED.gif" unknown="resources/icons/mediumschematics/LEDs/GRAYLED.gif" inconsistent="resources/icons/mediumschematics/LEDs/GRAYLED.gif" rotate="0" forcecontroloff="false" momentary="true" class="jmri.jmrit.display.configurexml.SensorIconXml" />
    <memoryicon        y="205" memory="IMTRK5H1" x="110" level="5" text="1899" size="13" style="0" selectable="no" class="jmri.jmrit.display.configurexml.MemoryIconXml" defaulticon="resources/icons/misc/X-red.gif" />
    <memoryicon        y="205" memory="IMTRK5H2" x="170" level="5" text="1899" size="13" style="0" selectable="no" class="jmri.jmrit.display.configurexml.MemoryIconXml" defaulticon="resources/icons/misc/X-red.gif" />
    <memoryicon        y="205" memory="IMTRK5T1" x="280" level="5" text="8503" size="13" style="0" selectable="no" class="jmri.jmrit.display.configurexml.MemoryIconXml" defaulticon="resources/icons/misc/X-red.gif" />
    <memoryicon        y="205" memory="IMTRK5T2" x="340" level="5" text="8503" size="13" style="0" selectable="no" class="jmri.jmrit.display.configurexml.MemoryIconXml" defaulticon="resources/icons/misc/X-red.gif" />

    <positionablelabel y="225" text="Track 6" x="19" forcecontroloff="false" fixed="false" showtooltip="true" class="jmri.jmrit.display.configurexml.PositionableLabelXml" level="5" size="13" style="0" />
    <sensoricon        y="225" sensor="CS2006" x="82" level="10" active="resources/icons/mediumschematics/LEDs/AMBERLED.gif" inactive="resources/icons/mediumschematics/LEDs/whiteLED.gif" unknown="resources/icons/mediumschematics/LEDs/GRAYLED.gif" inconsistent="resources/icons/mediumschematics/LEDs/GRAYLED.gif" rotate="0" forcecontroloff="false" momentary="true" class="jmri.jmrit.display.configurexml.SensorIconXml" />
    <memoryicon        y="225" memory="IMTRK6H1" x="110" level="5" text="1899" size="13" style="0" selectable="no" class="jmri.jmrit.display.configurexml.MemoryIconXml" defaulticon="resources/icons/misc/X-red.gif" />
    <memoryicon        y="225" memory="IMTRK6H2" x="170" level="5" text="1899" size="13" style="0" selectable="no" class="jmri.jmrit.display.configurexml.MemoryIconXml" defaulticon="resources/icons/misc/X-red.gif" />
    <memoryicon        y="225" memory="IMTRK6T1" x="280" level="5" text="8503" size="13" style="0" selectable="no" class="jmri.jmrit.display.configurexml.MemoryIconXml" defaulticon="resources/icons/misc/X-red.gif" />
    <memoryicon        y="225" memory="IMTRK6T2" x="340" level="5" text="8503" size="13" style="0" selectable="no" class="jmri.jmrit.display.configurexml.MemoryIconXml" defaulticon="resources/icons/misc/X-red.gif" />

    <positionablelabel y="245" text="Track 7" x="19" forcecontroloff="false" fixed="false" showtooltip="true" class="jmri.jmrit.display.configurexml.PositionableLabelXml" level="5" size="13" style="0" />
    <sensoricon        y="245" sensor="CS2007" x="82" level="10" active="resources/icons/mediumschematics/LEDs/AMBERLED.gif" inactive="resources/icons/mediumschematics/LEDs/whiteLED.gif" unknown="resources/icons/mediumschematics/LEDs/GRAYLED.gif" inconsistent="resources/icons/mediumschematics/LEDs/GRAYLED.gif" rotate="0" forcecontroloff="false" momentary="true" class="jmri.jmrit.display.configurexml.SensorIconXml" />
    <memoryicon        y="245" memory="IMTRK7H1" x="110" level="5" text="1899" size="13" style="0" selectable="no" class="jmri.jmrit.display.configurexml.MemoryIconXml" defaulticon="resources/icons/misc/X-red.gif" />
    <memoryicon        y="245" memory="IMTRK7H2" x="170" level="5" text="1899" size="13" style="0" selectable="no" class="jmri.jmrit.display.configurexml.MemoryIconXml" defaulticon="resources/icons/misc/X-red.gif" />
    <memoryicon        y="245" memory="IMTRK7T1" x="280" level="5" text="8503" size="13" style="0" selectable="no" class="jmri.jmrit.display.configurexml.MemoryIconXml" defaulticon="resources/icons/misc/X-red.gif" />
    <memoryicon        y="245" memory="IMTRK7T2" x="340" level="5" text="8503" size="13" style="0" selectable="no" class="jmri.jmrit.display.configurexml.MemoryIconXml" defaulticon="resources/icons/misc/X-red.gif" />

    <positionablelabel y="265" text="Track 8" x="19" forcecontroloff="false" fixed="false" showtooltip="true" class="jmri.jmrit.display.configurexml.PositionableLabelXml" level="5" size="13" style="0" />
    <sensoricon        y="265" sensor="CS2008" x="82" level="10" active="resources/icons/mediumschematics/LEDs/AMBERLED.gif" inactive="resources/icons/mediumschematics/LEDs/whiteLED.gif" unknown="resources/icons/mediumschematics/LEDs/GRAYLED.gif" inconsistent="resources/icons/mediumschematics/LEDs/GRAYLED.gif" rotate="0" forcecontroloff="false" momentary="true" class="jmri.jmrit.display.configurexml.SensorIconXml" />
    <memoryicon        y="265" memory="IMTRK8H1" x="110" level="5" text="1899" size="13" style="0" selectable="no" class="jmri.jmrit.display.configurexml.MemoryIconXml" defaulticon="resources/icons/misc/X-red.gif" />
    <memoryicon        y="265" memory="IMTRK8H2" x="170" level="5" text="1899" size="13" style="0" selectable="no" class="jmri.jmrit.display.configurexml.MemoryIconXml" defaulticon="resources/icons/misc/X-red.gif" />
    <memoryicon        y="265" memory="IMTRK8T1" x="280" level="5" text="8503" size="13" style="0" selectable="no" class="jmri.jmrit.display.configurexml.MemoryIconXml" defaulticon="resources/icons/misc/X-red.gif" />
    <memoryicon        y="265" memory="IMTRK8T2" x="340" level="5" text="8503" size="13" style="0" selectable="no" class="jmri.jmrit.display.configurexml.MemoryIconXml" defaulticon="resources/icons/misc/X-red.gif" />

    <positionablelabel y="285" text="Track 9" x="19" forcecontroloff="false" fixed="false" showtooltip="true" class="jmri.jmrit.display.configurexml.PositionableLabelXml" level="5" size="13" style="0" />
    <sensoricon        y="285" sensor="CS2009" x="82" level="10" active="resources/icons/mediumschematics/LEDs/AMBERLED.gif" inactive="resources/icons/mediumschematics/LEDs/whiteLED.gif" unknown="resources/icons/mediumschematics/LEDs/GRAYLED.gif" inconsistent="resources/icons/mediumschematics/LEDs/GRAYLED.gif" rotate="0" forcecontroloff="false" momentary="true" class="jmri.jmrit.display.configurexml.SensorIconXml" />
    <memoryicon        y="285" memory="IMTRK9H1" x="110" level="5" text="1899" size="13" style="0" selectable="no" class="jmri.jmrit.display.configurexml.MemoryIconXml" defaulticon="resources/icons/misc/X-red.gif" />
    <memoryicon        y="285" memory="IMTRK9H2" x="170" level="5" text="1899" size="13" style="0" selectable="no" class="jmri.jmrit.display.configurexml.MemoryIconXml" defaulticon="resources/icons/misc/X-red.gif" />
    <memoryicon        y="285" memory="IMTRK9T1" x="280" level="5" text="8503" size="13" style="0" selectable="no" class="jmri.jmrit.display.configurexml.MemoryIconXml" defaulticon="resources/icons/misc/X-red.gif" />
    <memoryicon        y="285" memory="IMTRK9T2" x="340" level="5" text="8503" size="13" style="0" selectable="no" class="jmri.jmrit.display.configurexml.MemoryIconXml" defaulticon="resources/icons/misc/X-red.gif" />

    <positionablelabel y="305" text="Track 10" x="19" forcecontroloff="false" fixed="false" showtooltip="true" class="jmri.jmrit.display.configurexml.PositionableLabelXml" level="5" size="13" style="0" />
    <sensoricon        y="305" sensor="CS2010" x="82" level="10" active="resources/icons/mediumschematics/LEDs/AMBERLED.gif" inactive="resources/icons/mediumschematics/LEDs/whiteLED.gif" unknown="resources/icons/mediumschematics/LEDs/GRAYLED.gif" inconsistent="resources/icons/mediumschematics/LEDs/GRAYLED.gif" rotate="0" forcecontroloff="false" momentary="true" class="jmri.jmrit.display.configurexml.SensorIconXml" />
    <memoryicon        y="305" memory="IMTRK10H1" x="110" level="5" text="1899" size="13" style="0" selectable="no" class="jmri.jmrit.display.configurexml.MemoryIconXml" defaulticon="resources/icons/misc/X-red.gif" />
    <memoryicon        y="305" memory="IMTRK10H2" x="170" level="5" text="1899" size="13" style="0" selectable="no" class="jmri.jmrit.display.configurexml.MemoryIconXml" defaulticon="resources/icons/misc/X-red.gif" />
    <memoryicon        y="305" memory="IMTRK10T1" x="280" level="5" text="8503" size="13" style="0" selectable="no" class="jmri.jmrit.display.configurexml.MemoryIconXml" defaulticon="resources/icons/misc/X-red.gif" />
    <memoryicon        y="305" memory="IMTRK10T2" x="340" level="5" text="8503" size="13" style="0" selectable="no" class="jmri.jmrit.display.configurexml.MemoryIconXml" defaulticon="resources/icons/misc/X-red.gif" />

    <positionablelabel y="325" text="Track 11" x="19" forcecontroloff="false" fixed="false" showtooltip="true" class="jmri.jmrit.display.configurexml.PositionableLabelXml" level="5" size="13" style="0" />
    <sensoricon        y="325" sensor="CS2011" x="82" level="10" active="resources/icons/mediumschematics/LEDs/AMBERLED.gif" inactive="resources/icons/mediumschematics/LEDs/whiteLED.gif" unknown="resources/icons/mediumschematics/LEDs/GRAYLED.gif" inconsistent="resources/icons/mediumschematics/LEDs/GRAYLED.gif" rotate="0" forcecontroloff="false" momentary="true" class="jmri.jmrit.display.configurexml.SensorIconXml" />
    <memoryicon        y="325" memory="IMTRK11H1" x="110" level="5" text="1899" size="13" style="0" selectable="no" class="jmri.jmrit.display.configurexml.MemoryIconXml" defaulticon="resources/icons/misc/X-red.gif" />
    <memoryicon        y="325" memory="IMTRK11H2" x="170" level="5" text="1899" size="13" style="0" selectable="no" class="jmri.jmrit.display.configurexml.MemoryIconXml" defaulticon="resources/icons/misc/X-red.gif" />
    <memoryicon        y="325" memory="IMTRK11T1" x="280" level="5" text="8503" size="13" style="0" selectable="no" class="jmri.jmrit.display.configurexml.MemoryIconXml" defaulticon="resources/icons/misc/X-red.gif" />
    <memoryicon        y="325" memory="IMTRK11T2" x="340" level="5" text="8503" size="13" style="0" selectable="no" class="jmri.jmrit.display.configurexml.MemoryIconXml" defaulticon="resources/icons/misc/X-red.gif" />

    <positionablelabel y="345" text="Track 12" x="19" forcecontroloff="false" fixed="false" showtooltip="true" class="jmri.jmrit.display.configurexml.PositionableLabelXml" level="5" size="13" style="0" />
    <sensoricon        y="345" sensor="CS2012" x="82" level="10" active="resources/icons/mediumschematics/LEDs/AMBERLED.gif" inactive="resources/icons/mediumschematics/LEDs/whiteLED.gif" unknown="resources/icons/mediumschematics/LEDs/GRAYLED.gif" inconsistent="resources/icons/mediumschematics/LEDs/GRAYLED.gif" rotate="0" forcecontroloff="false" momentary="true" class="jmri.jmrit.display.configurexml.SensorIconXml" />
    <memoryicon        y="345" memory="IMTRK12H1" x="110" level="5" text="1899" size="13" style="0" selectable="no" class="jmri.jmrit.display.configurexml.MemoryIconXml" defaulticon="resources/icons/misc/X-red.gif" />
    <memoryicon        y="345" memory="IMTRK12H2" x="170" level="5" text="1899" size="13" style="0" selectable="no" class="jmri.jmrit.display.configurexml.MemoryIconXml" defaulticon="resources/icons/misc/X-red.gif" />
    <memoryicon        y="345" memory="IMTRK12T1" x="280" level="5" text="8503" size="13" style="0" selectable="no" class="jmri.jmrit.display.configurexml.MemoryIconXml" defaulticon="resources/icons/misc/X-red.gif" />
    <memoryicon        y="345" memory="IMTRK12T2" x="340" level="5" text="8503" size="13" style="0" selectable="no" class="jmri.jmrit.display.configurexml.MemoryIconXml" defaulticon="resources/icons/misc/X-red.gif" />

    <positionablelabel y="365" text="Track 13" x="19" forcecontroloff="false" fixed="false" showtooltip="true" class="jmri.jmrit.display.configurexml.PositionableLabelXml" level="5" size="13" style="0" />
    <sensoricon        y="365" sensor="CS2013" x="82" level="10" active="resources/icons/mediumschematics/LEDs/AMBERLED.gif" inactive="resources/icons/mediumschematics/LEDs/whiteLED.gif" unknown="resources/icons/mediumschematics/LEDs/GRAYLED.gif" inconsistent="resources/icons/mediumschematics/LEDs/GRAYLED.gif" rotate="0" forcecontroloff="false" momentary="true" class="jmri.jmrit.display.configurexml.SensorIconXml" />
    <memoryicon        y="365" memory="IMTRK13H1" x="110" level="5" text="1899" size="13" style="0" selectable="no" class="jmri.jmrit.display.configurexml.MemoryIconXml" defaulticon="resources/icons/misc/X-red.gif" />
    <memoryicon        y="365" memory="IMTRK13H2" x="170" level="5" text="1899" size="13" style="0" selectable="no" class="jmri.jmrit.display.configurexml.MemoryIconXml" defaulticon="resources/icons/misc/X-red.gif" />
    <memoryicon        y="365" memory="IMTRK13T1" x="280" level="5" text="8503" size="13" style="0" selectable="no" class="jmri.jmrit.display.configurexml.MemoryIconXml" defaulticon="resources/icons/misc/X-red.gif" />
    <memoryicon        y="365" memory="IMTRK13T2" x="340" level="5" text="8503" size="13" style="0" selectable="no" class="jmri.jmrit.display.configurexml.MemoryIconXml" defaulticon="resources/icons/misc/X-red.gif" />

    <positionablelabel y="385" text="Track 14" x="19" forcecontroloff="false" fixed="false" showtooltip="true" class="jmri.jmrit.display.configurexml.PositionableLabelXml" level="5" size="13" style="0" />
    <sensoricon        y="385" sensor="CS2014" x="82" level="10" active="resources/icons/mediumschematics/LEDs/AMBERLED.gif" inactive="resources/icons/mediumschematics/LEDs/whiteLED.gif" unknown="resources/icons/mediumschematics/LEDs/GRAYLED.gif" inconsistent="resources/icons/mediumschematics/LEDs/GRAYLED.gif" rotate="0" forcecontroloff="false" momentary="true" class="jmri.jmrit.display.configurexml.SensorIconXml" />
    <memoryicon        y="385" memory="IMTRK14H1" x="110" level="5" text="1899" size="13" style="0" selectable="no" class="jmri.jmrit.display.configurexml.MemoryIconXml" defaulticon="resources/icons/misc/X-red.gif" />
    <memoryicon        y="385" memory="IMTRK14H2" x="170" level="5" text="1899" size="13" style="0" selectable="no" class="jmri.jmrit.display.configurexml.MemoryIconXml" defaulticon="resources/icons/misc/X-red.gif" />
    <memoryicon        y="385" memory="IMTRK14T1" x="280" level="5" text="8503" size="13" style="0" selectable="no" class="jmri.jmrit.display.configurexml.MemoryIconXml" defaulticon="resources/icons/misc/X-red.gif" />
    <memoryicon        y="385" memory="IMTRK14T2" x="340" level="5" text="8503" size="13" style="0" selectable="no" class="jmri.jmrit.display.configurexml.MemoryIconXml" defaulticon="resources/icons/misc/X-red.gif" />

    <positionablelabel y="405" text="Track 15" x="19" forcecontroloff="false" fixed="false" showtooltip="true" class="jmri.jmrit.display.configurexml.PositionableLabelXml" level="5" size="13" style="0" />
    <sensoricon        y="405" sensor="CS2015" x="82" level="10" active="resources/icons/mediumschematics/LEDs/AMBERLED.gif" inactive="resources/icons/mediumschematics/LEDs/whiteLED.gif" unknown="resources/icons/mediumschematics/LEDs/GRAYLED.gif" inconsistent="resources/icons/mediumschematics/LEDs/GRAYLED.gif" rotate="0" forcecontroloff="false" momentary="true" class="jmri.jmrit.display.configurexml.SensorIconXml" />
    <memoryicon        y="405" memory="IMTRK15H1" x="110" level="5" text="1899" size="13" style="0" selectable="no" class="jmri.jmrit.display.configurexml.MemoryIconXml" defaulticon="resources/icons/misc/X-red.gif" />
    <memoryicon        y="405" memory="IMTRK15H2" x="170" level="5" text="1899" size="13" style="0" selectable="no" class="jmri.jmrit.display.configurexml.MemoryIconXml" defaulticon="resources/icons/misc/X-red.gif" />
    <memoryicon        y="405" memory="IMTRK15T1" x="280" level="5" text="8503" size="13" style="0" selectable="no" class="jmri.jmrit.display.configurexml.MemoryIconXml" defaulticon="resources/icons/misc/X-red.gif" />
    <memoryicon        y="405" memory="IMTRK15T2" x="340" level="5" text="8503" size="13" style="0" selectable="no" class="jmri.jmrit.display.configurexml.MemoryIconXml" defaulticon="resources/icons/misc/X-red.gif" />

    <positionablelabel y="425" text="Machine 2" x="1" forcecontroloff="false" fixed="false" showtooltip="true" class="jmri.jmrit.display.configurexml.PositionableLabelXml" level="5" size="13" style="0" />
    <sensoricon        y="425" sensor="CS2016" x="82" level="10" active="resources/icons/mediumschematics/LEDs/AMBERLED.gif" inactive="resources/icons/mediumschematics/LEDs/whiteLED.gif" unknown="resources/icons/mediumschematics/LEDs/GRAYLED.gif" inconsistent="resources/icons/mediumschematics/LEDs/GRAYLED.gif" rotate="0" forcecontroloff="false" momentary="true" class="jmri.jmrit.display.configurexml.SensorIconXml" />
    <memoryicon        y="425" memory="IMTRKMACHINE2H1" x="110" level="5" text="1899" size="13" style="0" selectable="no" class="jmri.jmrit.display.configurexml.MemoryIconXml" defaulticon="resources/icons/misc/X-red.gif" />
    <memoryicon        y="425" memory="IMTRKMACHINE2H2" x="170" level="5" text="1899" size="13" style="0" selectable="no" class="jmri.jmrit.display.configurexml.MemoryIconXml" defaulticon="resources/icons/misc/X-red.gif" />
    <memoryicon        y="425" memory="IMTRKMACHINE2T1" x="280" level="5" text="8503" size="13" style="0" selectable="no" class="jmri.jmrit.display.configurexml.MemoryIconXml" defaulticon="resources/icons/misc/X-red.gif" />
    <memoryicon        y="425" memory="IMTRKMACHINE2T2" x="340" level="5" text="8503" size="13" style="0" selectable="no" class="jmri.jmrit.display.configurexml.MemoryIconXml" defaulticon="resources/icons/misc/X-red.gif" />

    <positionablelabel y="445" text="Machine 1" x="1" forcecontroloff="false" fixed="false" showtooltip="true" class="jmri.jmrit.display.configurexml.PositionableLabelXml" level="5" size="13" style="0" />
    <sensoricon        y="445" sensor="CS2017" x="82" level="10" active="resources/icons/mediumschematics/LEDs/AMBERLED.gif" inactive="resources/icons/mediumschematics/LEDs/whiteLED.gif" unknown="resources/icons/mediumschematics/LEDs/GRAYLED.gif" inconsistent="resources/icons/mediumschematics/LEDs/GRAYLED.gif" rotate="0" forcecontroloff="false" momentary="true" class="jmri.jmrit.display.configurexml.SensorIconXml" />
    <memoryicon        y="445" memory="IMTRKMACHINE1H1" x="110" level="5" text="1899" size="13" style="0" selectable="no" class="jmri.jmrit.display.configurexml.MemoryIconXml" defaulticon="resources/icons/misc/X-red.gif" />
    <memoryicon        y="445" memory="IMTRKMACHINE1H2" x="170" level="5" text="1899" size="13" style="0" selectable="no" class="jmri.jmrit.display.configurexml.MemoryIconXml" defaulticon="resources/icons/misc/X-red.gif" />
    <memoryicon        y="445" memory="IMTRKMACHINE1T1" x="280" level="5" text="8503" size="13" style="0" selectable="no" class="jmri.jmrit.display.configurexml.MemoryIconXml" defaulticon="resources/icons/misc/X-red.gif" />
    <memoryicon        y="445" memory="IMTRKMACHINE1T2" x="340" level="5" text="8503" size="13" style="0" selectable="no" class="jmri.jmrit.display.configurexml.MemoryIconXml" defaulticon="resources/icons/misc/X-red.gif" />

    <positionablelabel y="465" text="East Lead" x="1" forcecontroloff="false" fixed="false" showtooltip="true" class="jmri.jmrit.display.configurexml.PositionableLabelXml" level="5" size="13" style="0" />
    <sensoricon        y="465" sensor="CS2018" x="82" level="10" active="resources/icons/mediumschematics/LEDs/AMBERLED.gif" inactive="resources/icons/mediumschematics/LEDs/whiteLED.gif" unknown="resources/icons/mediumschematics/LEDs/GRAYLED.gif" inconsistent="resources/icons/mediumschematics/LEDs/GRAYLED.gif" rotate="0" forcecontroloff="false" momentary="true" class="jmri.jmrit.display.configurexml.SensorIconXml" />
    <memoryicon        y="465" memory="IMTRKEASTLEADH1" x="110" level="5" text="1899" size="13" style="0" selectable="no" class="jmri.jmrit.display.configurexml.MemoryIconXml" defaulticon="resources/icons/misc/X-red.gif" />
    <memoryicon        y="465" memory="IMTRKEASTLEADH2" x="170" level="5" text="1899" size="13" style="0" selectable="no" class="jmri.jmrit.display.configurexml.MemoryIconXml" defaulticon="resources/icons/misc/X-red.gif" />
    <memoryicon        y="465" memory="IMTRKEASTLEADT1" x="280" level="5" text="8503" size="13" style="0" selectable="no" class="jmri.jmrit.display.configurexml.MemoryIconXml" defaulticon="resources/icons/misc/X-red.gif" />
    <memoryicon        y="465" memory="IMTRKEASTLEADT2" x="340" level="5" text="8503" size="13" style="0" selectable="no" class="jmri.jmrit.display.configurexml.MemoryIconXml" defaulticon="resources/icons/misc/X-red.gif" />


    <positionablelabel y="495" text="Set" x="1" forcecontroloff="false" fixed="false" showtooltip="true" class="jmri.jmrit.display.configurexml.PositionableLabelXml" level="5" size="13" style="0" />
    <sensoricon        y="495" sensor="ISTRKSET" x="82" level="10" active="resources/icons/mediumschematics/LEDs/AMBERLED.gif" inactive="resources/icons/mediumschematics/LEDs/whiteLED.gif" unknown="resources/icons/mediumschematics/LEDs/GRAYLED.gif" inconsistent="resources/icons/mediumschematics/LEDs/GRAYLED.gif" rotate="0" forcecontroloff="false" momentary="true" class="jmri.jmrit.display.configurexml.SensorIconXml" />
    <memoryicon        y="495" memory="IMTRKSETH1" x="110" level="5" text="1899" size="13" style="0" selectable="no" class="jmri.jmrit.display.configurexml.MemoryIconXml" defaulticon="resources/icons/misc/X-red.gif" />
    <memoryicon        y="495" memory="IMTRKSETH2" x="170" level="5" text="1899" size="13" style="0" selectable="no" class="jmri.jmrit.display.configurexml.MemoryIconXml" defaulticon="resources/icons/misc/X-red.gif" />
    <memoryicon        y="495" memory="IMTRKSETT1" x="280" level="5" text="8503" size="13" style="0" selectable="no" class="jmri.jmrit.display.configurexml.MemoryIconXml" defaulticon="resources/icons/misc/X-red.gif" />
    <memoryicon        y="495" memory="IMTRKSETT2" x="340" level="5" text="8503" size="13" style="0" selectable="no" class="jmri.jmrit.display.configurexml.MemoryIconXml" defaulticon="resources/icons/misc/X-red.gif" />


    <positionablelabel y="524" text="Current" x="1" forcecontroloff="false" fixed="false" showtooltip="true" class="jmri.jmrit.display.configurexml.PositionableLabelXml" level="5" size="13" style="0" />
    <memoryicon        y="525" memory="IMTRKPOSITION" x="110" level="5" text="1899" size="13" style="0" selectable="no" class="jmri.jmrit.display.configurexml.MemoryIconXml" defaulticon="resources/icons/misc/X-red.gif" />
    <positionablelabel y="524" text="Last Mem" x="180" forcecontroloff="false" fixed="false" showtooltip="true" class="jmri.jmrit.display.configurexml.PositionableLabelXml" level="5" size="13" style="0" />
    <memoryicon        y="525" memory="IMTRKLASTMEM" x="300" level="5" text="1899" size="13" style="0" selectable="no" class="jmri.jmrit.display.configurexml.MemoryIconXml" defaulticon="resources/icons/misc/X-red.gif" />


    <positionablelabel forcecontroloff="false" fixed="false" showtooltip="true" class="jmri.jmrit.display.configurexml.PositionableLabelXml" x="110" y="7" level="5" text="Cab" size="13" style="0" />
    <sensoricon sensor="CS2024" x="150" y="7" level="10" active="resources/icons/mediumschematics/LEDs/AMBERLED.gif" inactive="resources/icons/mediumschematics/LEDs/whiteLED.gif" unknown="resources/icons/mediumschematics/LEDs/GRAYLED.gif" inconsistent="resources/icons/mediumschematics/LEDs/GRAYLED.gif" rotate="0" forcecontroloff="false" momentary="false" class="jmri.jmrit.display.configurexml.SensorIconXml" />
    <sensoricon sensor="CS2024" x="310" y="7" level="10" active="resources/icons/mediumschematics/LEDs/whiteLED.gif" inactive="resources/icons/mediumschematics/LEDs/AMBERLED.gif" unknown="resources/icons/mediumschematics/LEDs/GRAYLED.gif" inconsistent="resources/icons/mediumschematics/LEDs/GRAYLED.gif" rotate="0" forcecontroloff="false" momentary="false" class="jmri.jmrit.display.configurexml.SensorIconXml" />
    <positionablelabel forcecontroloff="false" fixed="false" showtooltip="true" class="jmri.jmrit.display.configurexml.PositionableLabelXml" x="340" y="8" level="5" text="Tail" size="13" style="0" />
  </paneleditor>
  <!--Written by JMRI version 2.5.1 on Sat Feb 21 10:54:44 PST 2009 $Id: XmlFile.java,v 1.38 2008/11/17 04:03:12 jacobsen Exp $-->
</layout-config>

